{
  "currentRound":104,
  "maxRounds":600,
  "player":{
    "id":1,
    "position":{
      "y":2,
      "x":714
    },
    "speed":9,
    "state":"NOTHING",
    "statesThatOccurredThisRound":[
      "NOTHING"
    ],
    "powerups":[
      "OIL",
      "OIL",
      "EMP",
      "TWEET",
      "EMP",
      "OIL",
      "TWEET",
      "TWEET",
      "EMP",
      "BOOST",
      "TWEET",
      "TWEET",
      "EMP",
      "TWEET",
      "OIL",
      "OIL",
      "OIL",
      "BOOST",
      "OIL",
      "OIL",
      "LIZARD",
      "LIZARD",
      "LIZARD",
      "EMP",
      "TWEET",
      "OIL",
      "LIZARD",
      "BOOST",
      "EMP",
      "LIZARD",
      "OIL"
    ],
    "boosting":false,
    "boostCounter":0,
    "damage":1,
    "score":157
  },
  "opponent":{
    "id":2,
    "position":{
      "y":4,
      "x":409
    },
    "speed":6
  },
  "worldMap":[
    [
      {
        "position":{
          "y":1,
          "x":709
        },
        "surfaceObject":0,
        "occupiedByPlayerId":0,
        "isOccupiedByCyberTruck":false
      },
      {
        "position":{
          "y":1,
          "x":710
        },
        "surfaceObject":0,
        "occupiedByPlayerId":0,
        "isOccupiedByCyberTruck":false
      },
      {
        "position":{
          "y":1,
          "x":711
        },
        "surfaceObject":0,
        "occupiedByPlayerId":0,
        "isOccupiedByCyberTruck":false
      },
      {
        "position":{
          "y":1,
          "x":712
        },
        "surfaceObject":0,
        "occupiedByPlayerId":0,
        "isOccupiedByCyberTruck":false
      },
      {
        "position":{
          "y":1,
          "x":713
        },
        "surfaceObject":7,
        "occupiedByPlayerId":0,
        "isOccupiedByCyberTruck":false
      },
      {
        "position":{
          "y":1,
          "x":714
        },
        "surfaceObject":0,
        "occupiedByPlayerId":0,
        "isOccupiedByCyberTruck":false
      },
      {
        "position":{
          "y":1,
          "x":715
        },
        "surfaceObject":0,
        "occupiedByPlayerId":0,
        "isOccupiedByCyberTruck":false
      },
      {
        "position":{
          "y":1,
          "x":716
        },
        "surfaceObject":0,
        "occupiedByPlayerId":0,
        "isOccupiedByCyberTruck":false
      },
      {
        "position":{
          "y":1,
          "x":717
        },
        "surfaceObject":0,
        "occupiedByPlayerId":0,
        "isOccupiedByCyberTruck":false
      },
      {
        "position":{
          "y":1,
          "x":718
        },
        "surfaceObject":0,
        "occupiedByPlayerId":0,
        "isOccupiedByCyberTruck":false
      },
      {
        "position":{
          "y":1,
          "x":719
        },
        "surfaceObject":0,
        "occupiedByPlayerId":0,
        "isOccupiedByCyberTruck":false
      },
      {
        "position":{
          "y":1,
          "x":720
        },
        "surfaceObject":1,
        "occupiedByPlayerId":0,
        "isOccupiedByCyberTruck":false
      },
      {
        "position":{
          "y":1,
          "x":721
        },
        "surfaceObject":0,
        "occupiedByPlayerId":0,
        "isOccupiedByCyberTruck":false
      },
      {
        "position":{
          "y":1,
          "x":722
        },
        "surfaceObject":0,
        "occupiedByPlayerId":0,
        "isOccupiedByCyberTruck":false
      },
      {
        "position":{
          "y":1,
          "x":723
        },
        "surfaceObject":0,
        "occupiedByPlayerId":0,
        "isOccupiedByCyberTruck":false
      },
      {
        "position":{
          "y":1,
          "x":724
        },
        "surfaceObject":0,
        "occupiedByPlayerId":0,
        "isOccupiedByCyberTruck":false
      },
      {
        "position":{
          "y":1,
          "x":725
        },
        "surfaceObject":0,
        "occupiedByPlayerId":0,
        "isOccupiedByCyberTruck":false
      },
      {
        "position":{
          "y":1,
          "x":726
        },
        "surfaceObject":0,
        "occupiedByPlayerId":0,
        "isOccupiedByCyberTruck":false
      },
      {
        "position":{
          "y":1,
          "x":727
        },
        "surfaceObject":0,
        "occupiedByPlayerId":0,
        "isOccupiedByCyberTruck":false
      },
      {
        "position":{
          "y":1,
          "x":728
        },
        "surfaceObject":0,
        "occupiedByPlayerId":0,
        "isOccupiedByCyberTruck":false
      },
      {
        "position":{
          "y":1,
          "x":729
        },
        "surfaceObject":0,
        "occupiedByPlayerId":0,
        "isOccupiedByCyberTruck":false
      },
      {
        "position":{
          "y":1,
          "x":730
        },
        "surfaceObject":0,
        "occupiedByPlayerId":0,
        "isOccupiedByCyberTruck":false
      },
      {
        "position":{
          "y":1,
          "x":731
        },
        "surfaceObject":0,
        "occupiedByPlayerId":0,
        "isOccupiedByCyberTruck":false
      },
      {
        "position":{
          "y":1,
          "x":732
        },
        "surfaceObject":0,
        "occupiedByPlayerId":0,
        "isOccupiedByCyberTruck":false
      },
      {
        "position":{
          "y":1,
          "x":733
        },
        "surfaceObject":0,
        "occupiedByPlayerId":0,
        "isOccupiedByCyberTruck":false
      },
      {
        "position":{
          "y":1,
          "x":734
        },
        "surfaceObject":3,
        "occupiedByPlayerId":0,
        "isOccupiedByCyberTruck":false
      }
    ],
    [
      {
        "position":{
          "y":2,
          "x":709
        },
        "surfaceObject":0,
        "occupiedByPlayerId":0,
        "isOccupiedByCyberTruck":false
      },
      {
        "position":{
          "y":2,
          "x":710
        },
        "surfaceObject":0,
        "occupiedByPlayerId":0,
        "isOccupiedByCyberTruck":false
      },
      {
        "position":{
          "y":2,
          "x":711
        },
        "surfaceObject":0,
        "occupiedByPlayerId":0,
        "isOccupiedByCyberTruck":false
      },
      {
        "position":{
          "y":2,
          "x":712
        },
        "surfaceObject":0,
        "occupiedByPlayerId":0,
        "isOccupiedByCyberTruck":false
      },
      {
        "position":{
          "y":2,
          "x":713
        },
        "surfaceObject":0,
        "occupiedByPlayerId":0,
        "isOccupiedByCyberTruck":false
      },
      {
        "position":{
          "y":2,
          "x":714
        },
        "surfaceObject":0,
        "occupiedByPlayerId":1,
        "isOccupiedByCyberTruck":false
      },
      {
        "position":{
          "y":2,
          "x":715
        },
        "surfaceObject":0,
        "occupiedByPlayerId":0,
        "isOccupiedByCyberTruck":false
      },
      {
        "position":{
          "y":2,
          "x":716
        },
        "surfaceObject":5,
        "occupiedByPlayerId":0,
        "isOccupiedByCyberTruck":false
      },
      {
        "position":{
          "y":2,
          "x":717
        },
        "surfaceObject":0,
        "occupiedByPlayerId":0,
        "isOccupiedByCyberTruck":false
      },
      {
        "position":{
          "y":2,
          "x":718
        },
        "surfaceObject":0,
        "occupiedByPlayerId":0,
        "isOccupiedByCyberTruck":false
      },
      {
        "position":{
          "y":2,
          "x":719
        },
        "surfaceObject":0,
        "occupiedByPlayerId":0,
        "isOccupiedByCyberTruck":false
      },
      {
        "position":{
          "y":2,
          "x":720
        },
        "surfaceObject":0,
        "occupiedByPlayerId":0,
        "isOccupiedByCyberTruck":false
      },
      {
        "position":{
          "y":2,
          "x":721
        },
        "surfaceObject":0,
        "occupiedByPlayerId":0,
        "isOccupiedByCyberTruck":false
      },
      {
        "position":{
          "y":2,
          "x":722
        },
        "surfaceObject":0,
        "occupiedByPlayerId":0,
        "isOccupiedByCyberTruck":false
      },
      {
        "position":{
          "y":2,
          "x":723
        },
        "surfaceObject":0,
        "occupiedByPlayerId":0,
        "isOccupiedByCyberTruck":false
      },
      {
        "position":{
          "y":2,
          "x":724
        },
        "surfaceObject":0,
        "occupiedByPlayerId":0,
        "isOccupiedByCyberTruck":false
      },
      {
        "position":{
          "y":2,
          "x":725
        },
        "surfaceObject":0,
        "occupiedByPlayerId":0,
        "isOccupiedByCyberTruck":false
      },
      {
        "position":{
          "y":2,
          "x":726
        },
        "surfaceObject":0,
        "occupiedByPlayerId":0,
        "isOccupiedByCyberTruck":false
      },
      {
        "position":{
          "y":2,
          "x":727
        },
        "surfaceObject":0,
        "occupiedByPlayerId":0,
        "isOccupiedByCyberTruck":false
      },
      {
        "position":{
          "y":2,
          "x":728
        },
        "surfaceObject":0,
        "occupiedByPlayerId":0,
        "isOccupiedByCyberTruck":false
      },
      {
        "position":{
          "y":2,
          "x":729
        },
        "surfaceObject":0,
        "occupiedByPlayerId":0,
        "isOccupiedByCyberTruck":false
      },
      {
        "position":{
          "y":2,
          "x":730
        },
        "surfaceObject":0,
        "occupiedByPlayerId":0,
        "isOccupiedByCyberTruck":false
      },
      {
        "position":{
          "y":2,
          "x":731
        },
        "surfaceObject":0,
        "occupiedByPlayerId":0,
        "isOccupiedByCyberTruck":false
      },
      {
        "position":{
          "y":2,
          "x":732
        },
        "surfaceObject":0,
        "occupiedByPlayerId":0,
        "isOccupiedByCyberTruck":false
      },
      {
        "position":{
          "y":2,
          "x":733
        },
        "surfaceObject":0,
        "occupiedByPlayerId":0,
        "isOccupiedByCyberTruck":false
      },
      {
        "position":{
          "y":2,
          "x":734
        },
        "surfaceObject":0,
        "occupiedByPlayerId":0,
        "isOccupiedByCyberTruck":false
      }
    ],
    [
      {
        "position":{
          "y":3,
          "x":709
        },
        "surfaceObject":0,
        "occupiedByPlayerId":0,
        "isOccupiedByCyberTruck":false
      },
      {
        "position":{
          "y":3,
          "x":710
        },
        "surfaceObject":0,
        "occupiedByPlayerId":0,
        "isOccupiedByCyberTruck":false
      },
      {
        "position":{
          "y":3,
          "x":711
        },
        "surfaceObject":0,
        "occupiedByPlayerId":0,
        "isOccupiedByCyberTruck":false
      },
      {
        "position":{
          "y":3,
          "x":712
        },
        "surfaceObject":0,
        "occupiedByPlayerId":0,
        "isOccupiedByCyberTruck":false
      },
      {
        "position":{
          "y":3,
          "x":713
        },
        "surfaceObject":0,
        "occupiedByPlayerId":0,
        "isOccupiedByCyberTruck":false
      },
      {
        "position":{
          "y":3,
          "x":714
        },
        "surfaceObject":0,
        "occupiedByPlayerId":0,
        "isOccupiedByCyberTruck":false
      },
      {
        "position":{
          "y":3,
          "x":715
        },
        "surfaceObject":0,
        "occupiedByPlayerId":0,
        "isOccupiedByCyberTruck":false
      },
      {
        "position":{
          "y":3,
          "x":716
        },
        "surfaceObject":0,
        "occupiedByPlayerId":0,
        "isOccupiedByCyberTruck":false
      },
      {
        "position":{
          "y":3,
          "x":717
        },
        "surfaceObject":0,
        "occupiedByPlayerId":0,
        "isOccupiedByCyberTruck":false
      },
      {
        "position":{
          "y":3,
          "x":718
        },
        "surfaceObject":0,
        "occupiedByPlayerId":0,
        "isOccupiedByCyberTruck":false
      },
      {
        "position":{
          "y":3,
          "x":719
        },
        "surfaceObject":1,
        "occupiedByPlayerId":0,
        "isOccupiedByCyberTruck":false
      },
      {
        "position":{
          "y":3,
          "x":720
        },
        "surfaceObject":0,
        "occupiedByPlayerId":0,
        "isOccupiedByCyberTruck":false
      },
      {
        "position":{
          "y":3,
          "x":721
        },
        "surfaceObject":0,
        "occupiedByPlayerId":0,
        "isOccupiedByCyberTruck":false
      },
      {
        "position":{
          "y":3,
          "x":722
        },
        "surfaceObject":0,
        "occupiedByPlayerId":0,
        "isOccupiedByCyberTruck":false
      },
      {
        "position":{
          "y":3,
          "x":723
        },
        "surfaceObject":0,
        "occupiedByPlayerId":0,
        "isOccupiedByCyberTruck":false
      },
      {
        "position":{
          "y":3,
          "x":724
        },
        "surfaceObject":0,
        "occupiedByPlayerId":0,
        "isOccupiedByCyberTruck":false
      },
      {
        "position":{
          "y":3,
          "x":725
        },
        "surfaceObject":0,
        "occupiedByPlayerId":0,
        "isOccupiedByCyberTruck":false
      },
      {
        "position":{
          "y":3,
          "x":726
        },
        "surfaceObject":0,
        "occupiedByPlayerId":0,
        "isOccupiedByCyberTruck":false
      },
      {
        "position":{
          "y":3,
          "x":727
        },
        "surfaceObject":0,
        "occupiedByPlayerId":0,
        "isOccupiedByCyberTruck":false
      },
      {
        "position":{
          "y":3,
          "x":728
        },
        "surfaceObject":0,
        "occupiedByPlayerId":0,
        "isOccupiedByCyberTruck":false
      },
      {
        "position":{
          "y":3,
          "x":729
        },
        "surfaceObject":0,
        "occupiedByPlayerId":0,
        "isOccupiedByCyberTruck":false
      },
      {
        "position":{
          "y":3,
          "x":730
        },
        "surfaceObject":0,
        "occupiedByPlayerId":0,
        "isOccupiedByCyberTruck":false
      },
      {
        "position":{
          "y":3,
          "x":731
        },
        "surfaceObject":0,
        "occupiedByPlayerId":0,
        "isOccupiedByCyberTruck":false
      },
      {
        "position":{
          "y":3,
          "x":732
        },
        "surfaceObject":0,
        "occupiedByPlayerId":0,
        "isOccupiedByCyberTruck":false
      },
      {
        "position":{
          "y":3,
          "x":733
        },
        "surfaceObject":0,
        "occupiedByPlayerId":0,
        "isOccupiedByCyberTruck":false
      },
      {
        "position":{
          "y":3,
          "x":734
        },
        "surfaceObject":0,
        "occupiedByPlayerId":0,
        "isOccupiedByCyberTruck":false
      }
    ],
    [
      {
        "position":{
          "y":4,
          "x":709
        },
        "surfaceObject":0,
        "occupiedByPlayerId":0,
        "isOccupiedByCyberTruck":false
      },
      {
        "position":{
          "y":4,
          "x":710
        },
        "surfaceObject":0,
        "occupiedByPlayerId":0,
        "isOccupiedByCyberTruck":false
      },
      {
        "position":{
          "y":4,
          "x":711
        },
        "surfaceObject":0,
        "occupiedByPlayerId":0,
        "isOccupiedByCyberTruck":false
      },
      {
        "position":{
          "y":4,
          "x":712
        },
        "surfaceObject":0,
        "occupiedByPlayerId":0,
        "isOccupiedByCyberTruck":false
      },
      {
        "position":{
          "y":4,
          "x":713
        },
        "surfaceObject":0,
        "occupiedByPlayerId":0,
        "isOccupiedByCyberTruck":false
      },
      {
        "position":{
          "y":4,
          "x":714
        },
        "surfaceObject":0,
        "occupiedByPlayerId":0,
        "isOccupiedByCyberTruck":false
      },
      {
        "position":{
          "y":4,
          "x":715
        },
        "surfaceObject":0,
        "occupiedByPlayerId":0,
        "isOccupiedByCyberTruck":false
      },
      {
        "position":{
          "y":4,
          "x":716
        },
        "surfaceObject":1,
        "occupiedByPlayerId":0,
        "isOccupiedByCyberTruck":false
      },
      {
        "position":{
          "y":4,
          "x":717
        },
        "surfaceObject":1,
        "occupiedByPlayerId":0,
        "isOccupiedByCyberTruck":false
      },
      {
        "position":{
          "y":4,
          "x":718
        },
        "surfaceObject":1,
        "occupiedByPlayerId":0,
        "isOccupiedByCyberTruck":false
      },
      {
        "position":{
          "y":4,
          "x":719
        },
        "surfaceObject":0,
        "occupiedByPlayerId":0,
        "isOccupiedByCyberTruck":false
      },
      {
        "position":{
          "y":4,
          "x":720
        },
        "surfaceObject":0,
        "occupiedByPlayerId":0,
        "isOccupiedByCyberTruck":false
      },
      {
        "position":{
          "y":4,
          "x":721
        },
        "surfaceObject":0,
        "occupiedByPlayerId":0,
        "isOccupiedByCyberTruck":false
      },
      {
        "position":{
          "y":4,
          "x":722
        },
        "surfaceObject":6,
        "occupiedByPlayerId":0,
        "isOccupiedByCyberTruck":false
      },
      {
        "position":{
          "y":4,
          "x":723
        },
        "surfaceObject":0,
        "occupiedByPlayerId":0,
        "isOccupiedByCyberTruck":false
      },
      {
        "position":{
          "y":4,
          "x":724
        },
        "surfaceObject":0,
        "occupiedByPlayerId":0,
        "isOccupiedByCyberTruck":false
      },
      {
        "position":{
          "y":4,
          "x":725
        },
        "surfaceObject":0,
        "occupiedByPlayerId":0,
        "isOccupiedByCyberTruck":false
      },
      {
        "position":{
          "y":4,
          "x":726
        },
        "surfaceObject":0,
        "occupiedByPlayerId":0,
        "isOccupiedByCyberTruck":false
      },
      {
        "position":{
          "y":4,
          "x":727
        },
        "surfaceObject":0,
        "occupiedByPlayerId":0,
        "isOccupiedByCyberTruck":false
      },
      {
        "position":{
          "y":4,
          "x":728
        },
        "surfaceObject":0,
        "occupiedByPlayerId":0,
        "isOccupiedByCyberTruck":false
      },
      {
        "position":{
          "y":4,
          "x":729
        },
        "surfaceObject":0,
        "occupiedByPlayerId":0,
        "isOccupiedByCyberTruck":false
      },
      {
        "position":{
          "y":4,
          "x":730
        },
        "surfaceObject":0,
        "occupiedByPlayerId":0,
        "isOccupiedByCyberTruck":false
      },
      {
        "position":{
          "y":4,
          "x":731
        },
        "surfaceObject":0,
        "occupiedByPlayerId":0,
        "isOccupiedByCyberTruck":false
      },
      {
        "position":{
          "y":4,
          "x":732
        },
        "surfaceObject":0,
        "occupiedByPlayerId":0,
        "isOccupiedByCyberTruck":false
      },
      {
        "position":{
          "y":4,
          "x":733
        },
        "surfaceObject":7,
        "occupiedByPlayerId":0,
        "isOccupiedByCyberTruck":false
      },
      {
        "position":{
          "y":4,
          "x":734
        },
        "surfaceObject":0,
        "occupiedByPlayerId":0,
        "isOccupiedByCyberTruck":false
      }
    ]
  ]
}