{
  "currentRound":153,
  "maxRounds":600,
  "player":{
    "id":2,
    "position":{
      "y":4,
      "x":568
    },
    "speed":3,
    "state":"ACCELERATING",
    "statesThatOccurredThisRound":[
      "ACCELERATING"
    ],
    "powerups":[
      "TWEET",
      "OIL",
      "TWEET",
      "OIL",
      "EMP",
      "OIL",
      "OIL",
      "TWEET",
      "OIL",
      "EMP",
      "EMP",
      "EMP",
      "OIL",
      "TWEET",
      "OIL",
      "EMP",
      "LIZARD",
      "OIL",
      "EMP",
      "OIL",
      "LIZARD",
      "EMP",
      "OIL",
      "TWEET",
      "OIL"
    ],
    "boosting":false,
    "boostCounter":0,
    "damage":4,
    "score":39
  },
  "opponent":{
    "id":1,
    "position":{
      "y":2,
      "x":1147
    },
    "speed":9
  },
  "worldMap":[
    [
      {
        "position":{
          "y":1,
          "x":563
        },
        "surfaceObject":8,
        "occupiedByPlayerId":0,
        "isOccupiedByCyberTruck":false
      },
      {
        "position":{
          "y":1,
          "x":564
        },
        "surfaceObject":0,
        "occupiedByPlayerId":0,
        "isOccupiedByCyberTruck":false
      },
      {
        "position":{
          "y":1,
          "x":565
        },
        "surfaceObject":0,
        "occupiedByPlayerId":0,
        "isOccupiedByCyberTruck":false
      },
      {
        "position":{
          "y":1,
          "x":566
        },
        "surfaceObject":0,
        "occupiedByPlayerId":0,
        "isOccupiedByCyberTruck":false
      },
      {
        "position":{
          "y":1,
          "x":567
        },
        "surfaceObject":3,
        "occupiedByPlayerId":0,
        "isOccupiedByCyberTruck":false
      },
      {
        "position":{
          "y":1,
          "x":568
        },
        "surfaceObject":0,
        "occupiedByPlayerId":0,
        "isOccupiedByCyberTruck":false
      },
      {
        "position":{
          "y":1,
          "x":569
        },
        "surfaceObject":0,
        "occupiedByPlayerId":0,
        "isOccupiedByCyberTruck":false
      },
      {
        "position":{
          "y":1,
          "x":570
        },
        "surfaceObject":0,
        "occupiedByPlayerId":0,
        "isOccupiedByCyberTruck":false
      },
      {
        "position":{
          "y":1,
          "x":571
        },
        "surfaceObject":0,
        "occupiedByPlayerId":0,
        "isOccupiedByCyberTruck":false
      },
      {
        "position":{
          "y":1,
          "x":572
        },
        "surfaceObject":0,
        "occupiedByPlayerId":0,
        "isOccupiedByCyberTruck":false
      },
      {
        "position":{
          "y":1,
          "x":573
        },
        "surfaceObject":0,
        "occupiedByPlayerId":0,
        "isOccupiedByCyberTruck":false
      },
      {
        "position":{
          "y":1,
          "x":574
        },
        "surfaceObject":0,
        "occupiedByPlayerId":0,
        "isOccupiedByCyberTruck":false
      },
      {
        "position":{
          "y":1,
          "x":575
        },
        "surfaceObject":0,
        "occupiedByPlayerId":0,
        "isOccupiedByCyberTruck":false
      },
      {
        "position":{
          "y":1,
          "x":576
        },
        "surfaceObject":0,
        "occupiedByPlayerId":0,
        "isOccupiedByCyberTruck":false
      },
      {
        "position":{
          "y":1,
          "x":577
        },
        "surfaceObject":0,
        "occupiedByPlayerId":0,
        "isOccupiedByCyberTruck":false
      },
      {
        "position":{
          "y":1,
          "x":578
        },
        "surfaceObject":0,
        "occupiedByPlayerId":0,
        "isOccupiedByCyberTruck":false
      },
      {
        "position":{
          "y":1,
          "x":579
        },
        "surfaceObject":0,
        "occupiedByPlayerId":0,
        "isOccupiedByCyberTruck":false
      },
      {
        "position":{
          "y":1,
          "x":580
        },
        "surfaceObject":1,
        "occupiedByPlayerId":0,
        "isOccupiedByCyberTruck":false
      },
      {
        "position":{
          "y":1,
          "x":581
        },
        "surfaceObject":0,
        "occupiedByPlayerId":0,
        "isOccupiedByCyberTruck":false
      },
      {
        "position":{
          "y":1,
          "x":582
        },
        "surfaceObject":0,
        "occupiedByPlayerId":0,
        "isOccupiedByCyberTruck":false
      },
      {
        "position":{
          "y":1,
          "x":583
        },
        "surfaceObject":0,
        "occupiedByPlayerId":0,
        "isOccupiedByCyberTruck":false
      },
      {
        "position":{
          "y":1,
          "x":584
        },
        "surfaceObject":7,
        "occupiedByPlayerId":0,
        "isOccupiedByCyberTruck":false
      },
      {
        "position":{
          "y":1,
          "x":585
        },
        "surfaceObject":5,
        "occupiedByPlayerId":0,
        "isOccupiedByCyberTruck":false
      },
      {
        "position":{
          "y":1,
          "x":586
        },
        "surfaceObject":0,
        "occupiedByPlayerId":0,
        "isOccupiedByCyberTruck":false
      },
      {
        "position":{
          "y":1,
          "x":587
        },
        "surfaceObject":0,
        "occupiedByPlayerId":0,
        "isOccupiedByCyberTruck":false
      },
      {
        "position":{
          "y":1,
          "x":588
        },
        "surfaceObject":0,
        "occupiedByPlayerId":0,
        "isOccupiedByCyberTruck":false
      }
    ],
    [
      {
        "position":{
          "y":2,
          "x":563
        },
        "surfaceObject":0,
        "occupiedByPlayerId":0,
        "isOccupiedByCyberTruck":false
      },
      {
        "position":{
          "y":2,
          "x":564
        },
        "surfaceObject":0,
        "occupiedByPlayerId":0,
        "isOccupiedByCyberTruck":false
      },
      {
        "position":{
          "y":2,
          "x":565
        },
        "surfaceObject":0,
        "occupiedByPlayerId":0,
        "isOccupiedByCyberTruck":false
      },
      {
        "position":{
          "y":2,
          "x":566
        },
        "surfaceObject":0,
        "occupiedByPlayerId":0,
        "isOccupiedByCyberTruck":false
      },
      {
        "position":{
          "y":2,
          "x":567
        },
        "surfaceObject":0,
        "occupiedByPlayerId":0,
        "isOccupiedByCyberTruck":false
      },
      {
        "position":{
          "y":2,
          "x":568
        },
        "surfaceObject":0,
        "occupiedByPlayerId":0,
        "isOccupiedByCyberTruck":false
      },
      {
        "position":{
          "y":2,
          "x":569
        },
        "surfaceObject":0,
        "occupiedByPlayerId":0,
        "isOccupiedByCyberTruck":false
      },
      {
        "position":{
          "y":2,
          "x":570
        },
        "surfaceObject":0,
        "occupiedByPlayerId":0,
        "isOccupiedByCyberTruck":false
      },
      {
        "position":{
          "y":2,
          "x":571
        },
        "surfaceObject":0,
        "occupiedByPlayerId":0,
        "isOccupiedByCyberTruck":false
      },
      {
        "position":{
          "y":2,
          "x":572
        },
        "surfaceObject":0,
        "occupiedByPlayerId":0,
        "isOccupiedByCyberTruck":false
      },
      {
        "position":{
          "y":2,
          "x":573
        },
        "surfaceObject":0,
        "occupiedByPlayerId":0,
        "isOccupiedByCyberTruck":false
      },
      {
        "position":{
          "y":2,
          "x":574
        },
        "surfaceObject":0,
        "occupiedByPlayerId":0,
        "isOccupiedByCyberTruck":false
      },
      {
        "position":{
          "y":2,
          "x":575
        },
        "surfaceObject":0,
        "occupiedByPlayerId":0,
        "isOccupiedByCyberTruck":false
      },
      {
        "position":{
          "y":2,
          "x":576
        },
        "surfaceObject":0,
        "occupiedByPlayerId":0,
        "isOccupiedByCyberTruck":false
      },
      {
        "position":{
          "y":2,
          "x":577
        },
        "surfaceObject":3,
        "occupiedByPlayerId":0,
        "isOccupiedByCyberTruck":false
      },
      {
        "position":{
          "y":2,
          "x":578
        },
        "surfaceObject":0,
        "occupiedByPlayerId":0,
        "isOccupiedByCyberTruck":false
      },
      {
        "position":{
          "y":2,
          "x":579
        },
        "surfaceObject":0,
        "occupiedByPlayerId":0,
        "isOccupiedByCyberTruck":false
      },
      {
        "position":{
          "y":2,
          "x":580
        },
        "surfaceObject":1,
        "occupiedByPlayerId":0,
        "isOccupiedByCyberTruck":false
      },
      {
        "position":{
          "y":2,
          "x":581
        },
        "surfaceObject":0,
        "occupiedByPlayerId":0,
        "isOccupiedByCyberTruck":false
      },
      {
        "position":{
          "y":2,
          "x":582
        },
        "surfaceObject":0,
        "occupiedByPlayerId":0,
        "isOccupiedByCyberTruck":false
      },
      {
        "position":{
          "y":2,
          "x":583
        },
        "surfaceObject":0,
        "occupiedByPlayerId":0,
        "isOccupiedByCyberTruck":false
      },
      {
        "position":{
          "y":2,
          "x":584
        },
        "surfaceObject":0,
        "occupiedByPlayerId":0,
        "isOccupiedByCyberTruck":false
      },
      {
        "position":{
          "y":2,
          "x":585
        },
        "surfaceObject":0,
        "occupiedByPlayerId":0,
        "isOccupiedByCyberTruck":false
      },
      {
        "position":{
          "y":2,
          "x":586
        },
        "surfaceObject":0,
        "occupiedByPlayerId":0,
        "isOccupiedByCyberTruck":false
      },
      {
        "position":{
          "y":2,
          "x":587
        },
        "surfaceObject":0,
        "occupiedByPlayerId":0,
        "isOccupiedByCyberTruck":false
      },
      {
        "position":{
          "y":2,
          "x":588
        },
        "surfaceObject":0,
        "occupiedByPlayerId":0,
        "isOccupiedByCyberTruck":false
      }
    ],
    [
      {
        "position":{
          "y":3,
          "x":563
        },
        "surfaceObject":0,
        "occupiedByPlayerId":0,
        "isOccupiedByCyberTruck":false
      },
      {
        "position":{
          "y":3,
          "x":564
        },
        "surfaceObject":0,
        "occupiedByPlayerId":0,
        "isOccupiedByCyberTruck":false
      },
      {
        "position":{
          "y":3,
          "x":565
        },
        "surfaceObject":0,
        "occupiedByPlayerId":0,
        "isOccupiedByCyberTruck":false
      },
      {
        "position":{
          "y":3,
          "x":566
        },
        "surfaceObject":0,
        "occupiedByPlayerId":0,
        "isOccupiedByCyberTruck":false
      },
      {
        "position":{
          "y":3,
          "x":567
        },
        "surfaceObject":0,
        "occupiedByPlayerId":0,
        "isOccupiedByCyberTruck":false
      },
      {
        "position":{
          "y":3,
          "x":568
        },
        "surfaceObject":0,
        "occupiedByPlayerId":0,
        "isOccupiedByCyberTruck":false
      },
      {
        "position":{
          "y":3,
          "x":569
        },
        "surfaceObject":0,
        "occupiedByPlayerId":0,
        "isOccupiedByCyberTruck":false
      },
      {
        "position":{
          "y":3,
          "x":570
        },
        "surfaceObject":0,
        "occupiedByPlayerId":0,
        "isOccupiedByCyberTruck":false
      },
      {
        "position":{
          "y":3,
          "x":571
        },
        "surfaceObject":0,
        "occupiedByPlayerId":0,
        "isOccupiedByCyberTruck":false
      },
      {
        "position":{
          "y":3,
          "x":572
        },
        "surfaceObject":0,
        "occupiedByPlayerId":0,
        "isOccupiedByCyberTruck":false
      },
      {
        "position":{
          "y":3,
          "x":573
        },
        "surfaceObject":0,
        "occupiedByPlayerId":0,
        "isOccupiedByCyberTruck":false
      },
      {
        "position":{
          "y":3,
          "x":574
        },
        "surfaceObject":0,
        "occupiedByPlayerId":0,
        "isOccupiedByCyberTruck":false
      },
      {
        "position":{
          "y":3,
          "x":575
        },
        "surfaceObject":0,
        "occupiedByPlayerId":0,
        "isOccupiedByCyberTruck":false
      },
      {
        "position":{
          "y":3,
          "x":576
        },
        "surfaceObject":0,
        "occupiedByPlayerId":0,
        "isOccupiedByCyberTruck":false
      },
      {
        "position":{
          "y":3,
          "x":577
        },
        "surfaceObject":0,
        "occupiedByPlayerId":0,
        "isOccupiedByCyberTruck":false
      },
      {
        "position":{
          "y":3,
          "x":578
        },
        "surfaceObject":0,
        "occupiedByPlayerId":0,
        "isOccupiedByCyberTruck":false
      },
      {
        "position":{
          "y":3,
          "x":579
        },
        "surfaceObject":0,
        "occupiedByPlayerId":0,
        "isOccupiedByCyberTruck":false
      },
      {
        "position":{
          "y":3,
          "x":580
        },
        "surfaceObject":0,
        "occupiedByPlayerId":0,
        "isOccupiedByCyberTruck":false
      },
      {
        "position":{
          "y":3,
          "x":581
        },
        "surfaceObject":0,
        "occupiedByPlayerId":0,
        "isOccupiedByCyberTruck":false
      },
      {
        "position":{
          "y":3,
          "x":582
        },
        "surfaceObject":0,
        "occupiedByPlayerId":0,
        "isOccupiedByCyberTruck":false
      },
      {
        "position":{
          "y":3,
          "x":583
        },
        "surfaceObject":0,
        "occupiedByPlayerId":0,
        "isOccupiedByCyberTruck":false
      },
      {
        "position":{
          "y":3,
          "x":584
        },
        "surfaceObject":0,
        "occupiedByPlayerId":0,
        "isOccupiedByCyberTruck":false
      },
      {
        "position":{
          "y":3,
          "x":585
        },
        "surfaceObject":0,
        "occupiedByPlayerId":0,
        "isOccupiedByCyberTruck":false
      },
      {
        "position":{
          "y":3,
          "x":586
        },
        "surfaceObject":0,
        "occupiedByPlayerId":0,
        "isOccupiedByCyberTruck":false
      },
      {
        "position":{
          "y":3,
          "x":587
        },
        "surfaceObject":0,
        "occupiedByPlayerId":0,
        "isOccupiedByCyberTruck":false
      },
      {
        "position":{
          "y":3,
          "x":588
        },
        "surfaceObject":0,
        "occupiedByPlayerId":0,
        "isOccupiedByCyberTruck":false
      }
    ],
    [
      {
        "position":{
          "y":4,
          "x":563
        },
        "surfaceObject":0,
        "occupiedByPlayerId":0,
        "isOccupiedByCyberTruck":false
      },
      {
        "position":{
          "y":4,
          "x":564
        },
        "surfaceObject":0,
        "occupiedByPlayerId":0,
        "isOccupiedByCyberTruck":false
      },
      {
        "position":{
          "y":4,
          "x":565
        },
        "surfaceObject":0,
        "occupiedByPlayerId":0,
        "isOccupiedByCyberTruck":false
      },
      {
        "position":{
          "y":4,
          "x":566
        },
        "surfaceObject":3,
        "occupiedByPlayerId":0,
        "isOccupiedByCyberTruck":false
      },
      {
        "position":{
          "y":4,
          "x":567
        },
        "surfaceObject":0,
        "occupiedByPlayerId":0,
        "isOccupiedByCyberTruck":false
      },
      {
        "position":{
          "y":4,
          "x":568
        },
        "surfaceObject":0,
        "occupiedByPlayerId":2,
        "isOccupiedByCyberTruck":false
      },
      {
        "position":{
          "y":4,
          "x":569
        },
        "surfaceObject":0,
        "occupiedByPlayerId":0,
        "isOccupiedByCyberTruck":false
      },
      {
        "position":{
          "y":4,
          "x":570
        },
        "surfaceObject":0,
        "occupiedByPlayerId":0,
        "isOccupiedByCyberTruck":false
      },
      {
        "position":{
          "y":4,
          "x":571
        },
        "surfaceObject":0,
        "occupiedByPlayerId":0,
        "isOccupiedByCyberTruck":false
      },
      {
        "position":{
          "y":4,
          "x":572
        },
        "surfaceObject":0,
        "occupiedByPlayerId":0,
        "isOccupiedByCyberTruck":false
      },
      {
        "position":{
          "y":4,
          "x":573
        },
        "surfaceObject":0,
        "occupiedByPlayerId":0,
        "isOccupiedByCyberTruck":false
      },
      {
        "position":{
          "y":4,
          "x":574
        },
        "surfaceObject":9,
        "occupiedByPlayerId":0,
        "isOccupiedByCyberTruck":false
      },
      {
        "position":{
          "y":4,
          "x":575
        },
        "surfaceObject":0,
        "occupiedByPlayerId":0,
        "isOccupiedByCyberTruck":false
      },
      {
        "position":{
          "y":4,
          "x":576
        },
        "surfaceObject":0,
        "occupiedByPlayerId":0,
        "isOccupiedByCyberTruck":false
      },
      {
        "position":{
          "y":4,
          "x":577
        },
        "surfaceObject":0,
        "occupiedByPlayerId":0,
        "isOccupiedByCyberTruck":false
      },
      {
        "position":{
          "y":4,
          "x":578
        },
        "surfaceObject":0,
        "occupiedByPlayerId":0,
        "isOccupiedByCyberTruck":false
      },
      {
        "position":{
          "y":4,
          "x":579
        },
        "surfaceObject":0,
        "occupiedByPlayerId":0,
        "isOccupiedByCyberTruck":false
      },
      {
        "position":{
          "y":4,
          "x":580
        },
        "surfaceObject":1,
        "occupiedByPlayerId":0,
        "isOccupiedByCyberTruck":false
      },
      {
        "position":{
          "y":4,
          "x":581
        },
        "surfaceObject":0,
        "occupiedByPlayerId":0,
        "isOccupiedByCyberTruck":false
      },
      {
        "position":{
          "y":4,
          "x":582
        },
        "surfaceObject":0,
        "occupiedByPlayerId":0,
        "isOccupiedByCyberTruck":false
      },
      {
        "position":{
          "y":4,
          "x":583
        },
        "surfaceObject":0,
        "occupiedByPlayerId":0,
        "isOccupiedByCyberTruck":false
      },
      {
        "position":{
          "y":4,
          "x":584
        },
        "surfaceObject":0,
        "occupiedByPlayerId":0,
        "isOccupiedByCyberTruck":false
      },
      {
        "position":{
          "y":4,
          "x":585
        },
        "surfaceObject":0,
        "occupiedByPlayerId":0,
        "isOccupiedByCyberTruck":false
      },
      {
        "position":{
          "y":4,
          "x":586
        },
        "surfaceObject":0,
        "occupiedByPlayerId":0,
        "isOccupiedByCyberTruck":false
      },
      {
        "position":{
          "y":4,
          "x":587
        },
        "surfaceObject":0,
        "occupiedByPlayerId":0,
        "isOccupiedByCyberTruck":false
      },
      {
        "position":{
          "y":4,
          "x":588
        },
        "surfaceObject":0,
        "occupiedByPlayerId":0,
        "isOccupiedByCyberTruck":false
      }
    ]
  ]
}